{
  "interactionModel": {
    "languageModel": {
      "invocationName": "gioco di indovinare il numero",
        "intents": [
        {
          "name": "AMAZON.CancelIntent",
          "samples": []
        },
        {
          "name": "AMAZON.HelpIntent",
          "samples": []
        },
        {
          "name": "AMAZON.StopIntent",
          "samples": []
        },
        {
          "name": "NumberGuessIntent",
          "samples": [
            "{number}",
            "è il {number}",
            "che ne dici del {number}",
            "può essere {number}",
            "dimmi se è il {number}"
          ],
          "slots": [{
              "name": "number", "type": "AMAZON.NUMBER"
              }]
        }
      ]
    }
  }
}
